<?xml version="1.0" encoding="UTF-8" standalone="yes"?>
<oracle-xsl-webmapper:StateInfo xmlns:oracle-xsl-webmapper="http://www.oracle.com/xsl/webmapper/state" version="1.1">
    <oracle-xsl-webmapper:ErrorsCount>0</oracle-xsl-webmapper:ErrorsCount>
    <oracle-xsl-webmapper:WarningsCount>0</oracle-xsl-webmapper:WarningsCount>
    <oracle-xsl-webmapper:IsImported>false</oracle-xsl-webmapper:IsImported>
    <oracle-xsl-webmapper:HasMappings>true</oracle-xsl-webmapper:HasMappings>
    <oracle-xsl-webmapper:StateInfoIsStale>false</oracle-xsl-webmapper:StateInfoIsStale>
    <oracle-xsl-webmapper:SourcesReferenced>
        <element xmlns:ns3="http://www.oracle.com/2014/03/ics/callout">ns3:output_JavaScriptFindIndex_res</element>
        <uriAbsoluteLocation>file:/tmp/WC/itg_e82d3de7-20e1-4c78-b74b-bc444f1222e7/resources/processor_113/resourcegroup_114/ICSCallout_Output.xsd</uriAbsoluteLocation>
        <param>JavaScriptFindIndex</param>
        <primary>false</primary>
    </oracle-xsl-webmapper:SourcesReferenced>
    <oracle-xsl-webmapper:SourcesReferenced>
        <element xmlns:ns3="http://www.oracle.com/2014/03/ics/callout">ns3:output_JavaScriptFindLastIndex_res</element>
        <uriAbsoluteLocation>file:/tmp/WC/itg_e82d3de7-20e1-4c78-b74b-bc444f1222e7/resources/processor_124/resourcegroup_125/ICSCallout_Output.xsd</uriAbsoluteLocation>
        <param>JavaScriptFindLastIndex</param>
        <primary>false</primary>
    </oracle-xsl-webmapper:SourcesReferenced>
    <oracle-xsl-webmapper:SourcesReferenced>
        <element xmlns:ns3="http://www.oracle.com/2014/03/ics/callout">ns3:output_JavaScriptContainSubstr_res</element>
        <uriAbsoluteLocation>file:/tmp/WC/itg_e82d3de7-20e1-4c78-b74b-bc444f1222e7/resources/processor_135/resourcegroup_136/ICSCallout_Output.xsd</uriAbsoluteLocation>
        <param>JavaScriptContainSubstr</param>
        <primary>false</primary>
    </oracle-xsl-webmapper:SourcesReferenced>
    <oracle-xsl-webmapper:SourcesReferenced>
        <element xmlns:ns3="http://www.oracle.com/2014/03/ics/callout">ns3:output_JavaScriptStartWithSubstr_res</element>
        <uriAbsoluteLocation>file:/tmp/WC/itg_e82d3de7-20e1-4c78-b74b-bc444f1222e7/resources/processor_146/resourcegroup_147/ICSCallout_Output.xsd</uriAbsoluteLocation>
        <param>JavaScriptStartWithSubstr</param>
        <primary>false</primary>
    </oracle-xsl-webmapper:SourcesReferenced>
    <oracle-xsl-webmapper:SourcesReferenced>
        <element xmlns:ns3="http://www.oracle.com/2014/03/ics/callout">ns3:output_JavaScriptEndWithSubstr_res</element>
        <uriAbsoluteLocation>file:/tmp/WC/itg_e82d3de7-20e1-4c78-b74b-bc444f1222e7/resources/processor_157/resourcegroup_158/ICSCallout_Output.xsd</uriAbsoluteLocation>
        <param>JavaScriptEndWithSubstr</param>
        <primary>false</primary>
    </oracle-xsl-webmapper:SourcesReferenced>
    <oracle-xsl-webmapper:AllSources>
        <element xmlns:ns3="http://xmlns.oracle.com/cloud/adapter/REST/string_REQUEST/jsSearch/types">ns3:execute</element>
        <uriAbsoluteLocation>file:/tmp/WC/itg_e82d3de7-20e1-4c78-b74b-bc444f1222e7/resources/application_10/outbound_11/resourcegroup_12/string_jsSearch_REQUEST.wsdl</uriAbsoluteLocation>
        <primary>true</primary>
    </oracle-xsl-webmapper:AllSources>
    <oracle-xsl-webmapper:AllSources>
        <element xmlns:ns3="http://www.oracle.com/2014/03/ics/callout">ns3:output_JavaScriptContainSubstr_res</element>
        <uriAbsoluteLocation>file:/tmp/WC/itg_e82d3de7-20e1-4c78-b74b-bc444f1222e7/resources/processor_135/resourcegroup_136/ICSCallout_Output.xsd</uriAbsoluteLocation>
        <param>JavaScriptContainSubstr</param>
        <primary>false</primary>
    </oracle-xsl-webmapper:AllSources>
    <oracle-xsl-webmapper:AllSources>
        <element xmlns:ns3="http://www.oracle.com/2014/03/ics/callout">ns3:output_JavaScriptEndWithSubstr_res</element>
        <uriAbsoluteLocation>file:/tmp/WC/itg_e82d3de7-20e1-4c78-b74b-bc444f1222e7/resources/processor_157/resourcegroup_158/ICSCallout_Output.xsd</uriAbsoluteLocation>
        <param>JavaScriptEndWithSubstr</param>
        <primary>false</primary>
    </oracle-xsl-webmapper:AllSources>
    <oracle-xsl-webmapper:AllSources>
        <element xmlns:ns3="http://www.oracle.com/2014/03/ics/callout">ns3:output_JavaScriptFindIndex_res</element>
        <uriAbsoluteLocation>file:/tmp/WC/itg_e82d3de7-20e1-4c78-b74b-bc444f1222e7/resources/processor_113/resourcegroup_114/ICSCallout_Output.xsd</uriAbsoluteLocation>
        <param>JavaScriptFindIndex</param>
        <primary>false</primary>
    </oracle-xsl-webmapper:AllSources>
    <oracle-xsl-webmapper:AllSources>
        <element xmlns:ns3="http://www.oracle.com/2014/03/ics/callout">ns3:output_JavaScriptFindLastIndex_res</element>
        <uriAbsoluteLocation>file:/tmp/WC/itg_e82d3de7-20e1-4c78-b74b-bc444f1222e7/resources/processor_124/resourcegroup_125/ICSCallout_Output.xsd</uriAbsoluteLocation>
        <param>JavaScriptFindLastIndex</param>
        <primary>false</primary>
    </oracle-xsl-webmapper:AllSources>
    <oracle-xsl-webmapper:AllSources>
        <element xmlns:ns3="http://www.oracle.com/2014/03/ics/callout">ns3:output_JavaScriptStartWithSubstr_res</element>
        <uriAbsoluteLocation>file:/tmp/WC/itg_e82d3de7-20e1-4c78-b74b-bc444f1222e7/resources/processor_146/resourcegroup_147/ICSCallout_Output.xsd</uriAbsoluteLocation>
        <param>JavaScriptStartWithSubstr</param>
        <primary>false</primary>
    </oracle-xsl-webmapper:AllSources>
</oracle-xsl-webmapper:StateInfo>